[
  {
    "label": "World Wide",
    "value": 1
  },
  {
    "label":"United Arab Emirates",
    "value":23424738
  },
  {
    "label":"Algeria",
    "value":23424740
  },
  {
    "label":"Argentina",
    "value":23424747
  },
  {
    "label":"Australia",
    "value":23424748
  },
  {
    "label":"Austria",
    "value":23424750
  },
  {
    "label":"Bahrain",
    "value":23424753
  },
  {
    "label":"Belgium",
    "value":23424757
  },
  {
    "label":"Belarus",
    "value":23424765
  },
  {
    "label":"Brazil",
    "value":23424768
  },
  {
    "label":"Canada",
    "value":23424775
  },
  {
    "label":"Chile",
    "value":23424782
  },
  {
    "label":"Colombia",
    "value":23424787
  },
  {
    "label":"Denmark",
    "value":23424796
  },
  {
    "label":"Dominican Republic",
    "value":23424800
  },
  {
    "label":"Ecuador",
    "value":23424801
  },
  {
    "label":"Egypt",
    "value":23424802
  },
  {
    "label":"Ireland",
    "value":23424803
  },
  {
    "label":"France",
    "value":23424819
  },
  {
    "label":"Ghana",
    "value":23424824
  },
  {
    "label":"Germany",
    "value":23424829
  },
  {
    "label":"Greece",
    "value":23424833
  },
  {
    "label":"Guatemala",
    "value":23424834
  },
  {
    "label":"Indonesia",
    "value":23424846
  },
  {
    "label":"India",
    "value":23424848
  },
  {
    "label":"Israel",
    "value":23424852
  },
  {
    "label":"Italy",
    "value":23424853
  },
  {
    "label":"Japan",
    "value":23424856
  },
  {
    "label":"Jordan",
    "value":23424860
  },
  {
    "label":"Kenya",
    "value":23424863
  },
  {
    "label":"Korea",
    "value":23424868
  },
  {
    "label":"Kuwait",
    "value":23424870
  },
  {
    "label":"Lebanon",
    "value":23424873
  },
  {
    "label":"Latvia",
    "value":23424874
  },
  {
    "label":"Oman",
    "value":23424898
  },
  {
    "label":"Mexico",
    "value":23424900
  },
  {
    "label":"Malaysia",
    "value":23424901
  },
  {
    "label":"Nigeria",
    "value":23424908
  },
  {
    "label":"Netherlands",
    "value":23424909
  },
  {
    "label":"Norway",
    "value":23424910
  },
  {
    "label":"New Zealand",
    "value":23424916
  },
  {
    "label":"Peru",
    "value":23424919
  },
  {
    "label":"Pakistan",
    "value":23424922
  },
  {
    "label":"Poland",
    "value":23424923
  },
  {
    "label":"Panama",
    "value":23424924
  },
  {
    "label":"Portugal",
    "value":23424925
  },
  {
    "label":"Qatar",
    "value":23424930
  },
  {
    "label":"Philippines",
    "value":23424934
  },
  {
    "label":"Puerto Rico",
    "value":23424935
  },
  {
    "label":"Russia",
    "value":23424936
  },
  {
    "label":"Saudi Arabia",
    "value":23424938
  },
  {
    "label":"South Africa",
    "value":23424942
  },
  {
    "label":"Singapore",
    "value":23424948
  },
  {
    "label":"Spain",
    "value":23424950
  },
  {
    "label":"Sweden",
    "value":23424954
  },
  {
    "label":"Switzerland",
    "value":23424957
  },
  {
    "label":"Thailand",
    "value":23424960
  },
  {
    "label":"Turkey",
    "value":23424969
  },
  {
    "label":"United Kingdom",
    "value":23424975
  },
  {
    "label":"Ukraine",
    "value":23424976
  },
  {
    "label":"United States",
    "value":23424977
  },
  {
    "label":"Venezuela",
    "value":23424982
  },
  {
    "label":"Vietnam",
    "value":23424984
  }
]